PolyMID/Correct.py
PolyMID/Natural.py
PolyMID/__init__.py
PolyMID/Classes/AtomClass.py
PolyMID/Classes/FormulaClass.py
PolyMID/Classes/FragmentClass.py
PolyMID/Classes/InputClass.py
PolyMID/Classes/TracerClass.py
PolyMID/Classes/__init__.py
PolyMID/SupportingFiles/AtomIMDs.txt
PolyMID/SupportingFiles/AtomIMDsHighRes.txt
PolyMID/SupportingFiles/ExampleInput.txt
PolyMID/SupportingFiles/__init__.py
PolyMID/SupportingFunctions/PadToEqualLength.py
PolyMID/SupportingFunctions/TextToCM.py
PolyMID/SupportingFunctions/__init__.py
PolyMID/SupportingFunctions/expand_polynomial.py
PolyMID/SupportingFunctions/get_directory.py
PolyMID/SupportingFunctions/quantity_of_atom.py
PolyMID-0.0.6.dist-info/LICENSE
PolyMID-0.0.6.dist-info/METADATA
PolyMID-0.0.6.dist-info/WHEEL
PolyMID-0.0.6.dist-info/top_level.txt
PolyMID-0.0.6.dist-info/RECORD
