Metadata-Version: 2.1
Name: PolyMID
Version: 0.0.6
Summary: PolyMID is a software package for analyzing stable-isotope tracing data.
Home-page: https://github.com/VacantiLab/PolyMID
Author: Nathaniel M Vaanti
Author-email: 
License: UNKNOWN
Platform: UNKNOWN
Classifier: Programming Language :: Python :: 3
Classifier: License :: OSI Approved :: MIT License
Classifier: Operating System :: OS Independent
Requires-Python: >=3.6
Requires-Dist: numpy
Requires-Dist: pandas
Requires-Dist: tk
